{
   "floater": {
      "@name": "object_vram_usage",
      "@title": {
         "string": "Object impact on VRAM"
      },
      "scroll_list:result_list": {
         "@name": "result_list",
         "column:uuid": {
            "@name": "uuid",
            "@label": {
               "string": "uuid"
            }
         },
         "column:name": {
            "@name": "name",
            "@label": {
               "string": "Name"
            }
         },
         "column:distance": {
            "@name": "distance",
            "@label": {
               "string": "Distance"
            }
         },
         "column:faces": {
            "@name": "faces",
            "@label": {
               "string": "Faces"
            }
         },
         "column:vertices": {
            "@name": "vertices",
            "@label": {
               "string": "Vertices"
            }
         },
         "column:indices": {
            "@name": "indices",
            "@label": {
               "string": "Indices"
            }
         },
         "column:vram_usage": {
            "@name": "vram_usage",
            "@label": {
               "string": "VRAM (Textures) in KB"
            }
         },
         "column:vram_usage_vbo": {
            "@name": "vram_usage_vbo",
            "@label": {
               "string": "VRAM (VBO) in KB"
            }
         }
      },
      "button:refresh_button": {
         "@label": {
            "string": "Refresh"
         },
         "@name": "refresh_button"
      }
   }
}